enlilviz/__init__.py
enlilviz/enlil.py
enlilviz/io.py
enlilviz/plotting/__init__.py
enlilviz/plotting/forecaster.py
enlilviz/plotting/plots.py
enlilviz-0.2.0.dist-info/AUTHORS.rst
enlilviz-0.2.0.dist-info/LICENSE
enlilviz-0.2.0.dist-info/METADATA
enlilviz-0.2.0.dist-info/WHEEL
enlilviz-0.2.0.dist-info/top_level.txt
enlilviz-0.2.0.dist-info/RECORD
