Metadata-Version: 2.1
Name: enlilviz
Version: 0.2.0
Summary: A Python package for visualizing output from the Enlil code.
Author-email: Greg Lucas <greg.lucas@lasp.colorado.edu>
License: MIT License
Project-URL: homepage, https://github.com/SWxTREC/enlilviz
Project-URL: documentation, https://enlilviz.readthedocs.io
Project-URL: repository, https://github.com/SWxTREC/enlilviz
Keywords: Enlil,Visualization
Classifier: Development Status :: 2 - Pre-Alpha
Classifier: Intended Audience :: Developers
Classifier: License :: OSI Approved :: MIT License
Classifier: Natural Language :: English
Classifier: Programming Language :: Python :: 3
Classifier: Programming Language :: Python :: 3.8
Classifier: Programming Language :: Python :: 3.9
Classifier: Programming Language :: Python :: 3.10
Classifier: Programming Language :: Python :: 3.11
Requires-Python: >=3.8
License-File: LICENSE
License-File: AUTHORS.rst
Requires-Dist: numpy
Requires-Dist: matplotlib
Requires-Dist: xarray
Requires-Dist: netcdf4
Provides-Extra: test
Requires-Dist: pytest (>=3) ; extra == 'test'
